MANIFEST.in
README.rst
setup.py
IChemPhy/Physics.py
IChemPhy/__init__.py
IChemPhy/Physics/Dynamics.py
IChemPhy/Physics/ElectroMagnetism.py
IChemPhy/Physics/__init__.py
IChemPhy/Physics/Dynamics/__init__.py
IChemPhy/Physics/Dynamics/pendulum.py
IChemPhy/Physics/Dynamics/projectile.py
IChemPhy/Physics/ElectroMagnetism/__init__.py
IChemPhy/Physics/ElectroMagnetism/electricField.py
IChemPhy/Physics/ElectroMagnetism/electricField2.py
IChemPhy/Physics/ElectroMagnetism/electricRod.py
IChemPhy/Physics/ElectroMagnetism/trajectory.py
IChemphy.egg-info/PKG-INFO
IChemphy.egg-info/SOURCES.txt
IChemphy.egg-info/dependency_links.txt
IChemphy.egg-info/not-zip-safe
IChemphy.egg-info/requires.txt
IChemphy.egg-info/top_level.txt