Metadata-Version: 1.1
Name: IChemphy
Version: 0.47
Summary: Physics and Chemistry Functions for GSU
Home-page: https://github.com/Lokesh523s/gsu_package
Author: Lokesh Sannuthi
Author-email: lokesh523s@gmail.com
License: MIT
Keywords: physics chemistry dynamics simulation python projectile pendulum electromagentic trajectory
Platform: UNKNOWN
Classifier: Development Status :: 3 - Alpha
Classifier: Programming Language :: Python :: 3.6
Classifier: Topic :: Education
